mcp_openapi_proxy/__init__.py
mcp_openapi_proxy/handlers.py
mcp_openapi_proxy/logging_setup.py
mcp_openapi_proxy/openapi.py
mcp_openapi_proxy/server_fastmcp.py
mcp_openapi_proxy/server_lowlevel.py
mcp_openapi_proxy/types.py
mcp_openapi_proxy/utils.py
ynet_api2mcp-0.1.0.dist-info/licenses/LICENSE
ynet_api2mcp-0.1.0.dist-info/METADATA
ynet_api2mcp-0.1.0.dist-info/WHEEL
ynet_api2mcp-0.1.0.dist-info/entry_points.txt
ynet_api2mcp-0.1.0.dist-info/top_level.txt
ynet_api2mcp-0.1.0.dist-info/RECORD
